routx-1.0.3.dist-info/METADATA
routx-1.0.3.dist-info/WHEEL
.routx.mesonpy.libs/libroutx.so
routx/__init__.py
routx/py.typed
routx/wrapper.py
routx-1.0.3.dist-info/RECORD
