Metadata-Version: 2.1
Name: routx
Version: 1.0.3
Author-Email: =?utf-8?q?Miko=C5=82aj_Kuranowski?= <mkuranowski@gmail.com>
Requires-Python: ~=3.10
Requires-Dist: typing-extensions~=4.15
